EHRPOP/__init__.py
EHRPOP/all_codes.json
EHRPOP/module.py
EHRPOP/utils.py
EHRPOP-0.0.9.dist-info/METADATA
EHRPOP-0.0.9.dist-info/WHEEL
EHRPOP-0.0.9.dist-info/top_level.txt
EHRPOP-0.0.9.dist-info/RECORD
