Metadata-Version: 2.1
Name: EHRPOP
Version: 0.0.9
Summary: SNDS Patients caracterzations
Home-page: https://github.com/HoussemNeuer
Author: AZZAG Houssem Eddine
Author-email: houssem-eddine.azzag@univ-amu.fr
Classifier: Programming Language :: Python :: 3
Classifier: License :: OSI Approved :: MIT License
Classifier: Operating System :: OS Independent
Requires-Python: >=3.6
Requires-Dist: numpy
Requires-Dist: plotly
Requires-Dist: pandas
Requires-Dist: regex
